xyzssh/__init__.py
xyzssh/setup.py
xyzssh-0.1.dist-info/METADATA
xyzssh-0.1.dist-info/WHEEL
xyzssh-0.1.dist-info/top_level.txt
xyzssh-0.1.dist-info/RECORD
