Metadata-Version: 2.1
Name: xyzssh
Version: 0.1
Summary: Une brève description du projet
Home-page: https://github.com/votre-nom/nom-du-projet
Author: xyz.ssh
Author-email: d3x73rstresser@gmail.com
License: MIT
Keywords: quelques mots clés pour votre projet
Classifier: Development Status :: 3 - Alpha
Classifier: Intended Audience :: Developers
Classifier: License :: OSI Approved :: MIT License
Classifier: Programming Language :: Python :: 3
Classifier: Programming Language :: Python :: 3.6
Classifier: Programming Language :: Python :: 3.7
Classifier: Programming Language :: Python :: 3.8
Classifier: Programming Language :: Python :: 3.9
Classifier: Programming Language :: Python :: 3 :: Only
Requires-Python: >=3.6
